vplog/__init__.py
vplog-0.1.3.dist-info/licenses/LICENSE
vplog-0.1.3.dist-info/METADATA
vplog-0.1.3.dist-info/WHEEL
vplog-0.1.3.dist-info/top_level.txt
vplog-0.1.3.dist-info/RECORD
