Metadata-Version: 2.4
Name: vplog
Version: 0.1.3
Summary: Redirects print() to timestamped log files.
Author-email: vofen <vofen430181@gmail.com>
License: MIT License
Requires-Python: >=3.8
License-File: LICENSE
Requires-Dist: loguru>=0.7
Dynamic: license-file
